{
  "id": "terminology",
  "title": "9 - Terminology",
  "description": "- Product: A course, consultation, or download package.",
  "source": "@site/docs/terminology.md",
  "sourceDirName": ".",
  "slug": "/terminology",
  "permalink": "/docs/terminology",
  "draft": false,
  "unlisted": false,
  "editUrl": "https://github.com/facebook/docusaurus/tree/main/packages/create-docusaurus/templates/shared/docs/terminology.md",
  "tags": [],
  "version": "current",
  "sidebarPosition": 9,
  "frontMatter": {
    "title": "9 - Terminology",
    "sidebar_position": 9
  },
  "sidebar": "tutorialSidebar",
  "previous": {
    "title": "8 - Key User Flows",
    "permalink": "/docs/user-flows"
  },
  "next": {
    "title": "10 - Playbooks",
    "permalink": "/docs/category/10---playbooks"
  }
}